sldatasets/__init__.py
sldatasets/datasethandler.py
sldatasets/lsa64.py
sldatasets-0.0.1.dist-info/LICENSE
sldatasets-0.0.1.dist-info/METADATA
sldatasets-0.0.1.dist-info/WHEEL
sldatasets-0.0.1.dist-info/top_level.txt
sldatasets-0.0.1.dist-info/RECORD
